wagtailenforcer/__init__.py
wagtailenforcer/admin_urls.py
wagtailenforcer/exceptions.py
wagtailenforcer/signals.py
wagtailenforcer/urls.py
wagtailenforcer/utilities.py
wagtailenforcer/validators.py
wagtailenforcer/views.py
wagtailenforcer/wagtail_hooks.py
wagtailenforcer/forms/__init__.py
wagtailenforcer/forms/wagtailadmin.py
wagtailenforcer/forms/wagtailusers.py
wagtailenforcer/middleware/__init__.py
wagtailenforcer/middleware/wagtail_enforcer_middleware.py
wagtailenforcer/templates/wagtailadmin/account/password_reset/enforce_confirm.html
wagtailenforcer/templates/wagtailenforcer/attempts.html
wagtailenforcer/templates/wagtailenforcer/list_attempts.html
wagtailenforcer/templates/wagtailenforcer/lockout.html
wagtailenforcer/templates/wagtailenforcer/includes/pagination_nav.html
wagtailenforcer/views/__init__.py
wagtailenforcer/views/axes/__init__.py
wagtailenforcer/views/axes/views.py
wagtailenforcer/views/wagtailusers/__init__.py
wagtailenforcer/views/wagtailusers/users.py
wagtailenforcer-1.0.2.dist-info/DESCRIPTION.rst
wagtailenforcer-1.0.2.dist-info/METADATA
wagtailenforcer-1.0.2.dist-info/metadata.json
wagtailenforcer-1.0.2.dist-info/RECORD
wagtailenforcer-1.0.2.dist-info/top_level.txt
wagtailenforcer-1.0.2.dist-info/WHEEL
