Metadata-Version: 2.0
Name: wagtailenforcer
Version: 1.0.2
Summary: WagtailEnforcer, the Wagtail arm of the law.
Home-page: https://github.com/springload/wagtailenforcer/
Author: Jordi J. Tablada, Dave Cartwright
Author-email: jordi@springload.co.nz, dave@springload.co.nz
License: BSD
Platform: UNKNOWN
Classifier: Programming Language :: Python
Classifier: Programming Language :: Python :: 2
Classifier: Programming Language :: Python :: 2.6
Classifier: Programming Language :: Python :: 2.7
Classifier: Programming Language :: Python :: 3
Classifier: Programming Language :: Python :: 3.2
Classifier: Programming Language :: Python :: 3.3
Classifier: Programming Language :: Python :: 3.4
Classifier: Framework :: Django
Requires-Dist: wagtail (>=1.3)
Requires-Dist: django (>=1.8)
Requires-Dist: django-password-policies
Requires-Dist: django-axes
Requires-Dist: pyclamd
